mcp_server_architect/__init__.py
mcp_server_architect/__main__.py
mcp_server_architect/core.py
mcp_server_architect/models.py
mcp_server_architect/types.py
mcp_server_architect/version.py
mcp_server_architect/agents/__init__.py
mcp_server_architect/agents/executor.py
mcp_server_architect/tools/__init__.py
mcp_server_architect/tools/code_reader.py
mcp_server_architect/tools/llm.py
mcp_server_architect/tools/web_search.py
mcp_server_architect-0.2.2.dist-info/METADATA
mcp_server_architect-0.2.2.dist-info/WHEEL
mcp_server_architect-0.2.2.dist-info/entry_points.txt
mcp_server_architect-0.2.2.dist-info/licenses/LICENSE
mcp_server_architect-0.2.2.dist-info/RECORD
