Metadata-Version: 2.4
Name: mcp-server-architect
Version: 0.2.2
Summary: AI Software Architect MCP Server that generates PRDs and provides reasoning assistance
Author: Greg Funtusov
License: MIT
License-File: LICENSE
Keywords: architecture,design,llm,mcp,prd
Classifier: Development Status :: 4 - Beta
Classifier: Intended Audience :: Developers
Classifier: License :: OSI Approved :: MIT License
Classifier: Programming Language :: Python :: 3
Classifier: Programming Language :: Python :: 3.10
Classifier: Programming Language :: Python :: 3.11
Requires-Python: >=3.10
Requires-Dist: anthropic>=0.49.0
Requires-Dist: exa-py
Requires-Dist: google-genai
Requires-Dist: httpx>=0.28.1
Requires-Dist: litellm>=1.65.0
Requires-Dist: logfire>=3.11.0
Requires-Dist: mcp[cli]
Requires-Dist: pydantic-ai
Requires-Dist: python-dotenv>=1.0.0
Requires-Dist: requests
Provides-Extra: dev
Requires-Dist: build>=1.0.0; extra == 'dev'
Requires-Dist: pytest-asyncio>=0.24.0; extra == 'dev'
Requires-Dist: pytest-recording>=0.13.0; extra == 'dev'
Requires-Dist: pytest>=7.0.0; extra == 'dev'
Requires-Dist: ruff>=0.3.0; extra == 'dev'
Requires-Dist: twine>=4.0.0; extra == 'dev'
